RemotePyLib/Exceptions.py
RemotePyLib/__init__.py
RemotePyLib/_internals.py
RemotePyLib-1.0.2.dist-info/LICENSE
RemotePyLib-1.0.2.dist-info/METADATA
RemotePyLib-1.0.2.dist-info/WHEEL
RemotePyLib-1.0.2.dist-info/top_level.txt
RemotePyLib-1.0.2.dist-info/RECORD
