Metadata-Version: 2.1
Name: RemotePyLib
Version: 1.0.2
Summary: A package to import libraries remotely.
Home-page: http://www.nalinangrish.me/apps/remotepylib
Author: Nalin Angrish
Author-email: nalin@nalinangrish.me
License: UNKNOWN
Platform: UNKNOWN
Classifier: Programming Language :: Python :: 3
Classifier: License :: OSI Approved :: MIT License
Classifier: Operating System :: OS Independent
Requires-Python: >=3.0
Requires-Dist: requests
Requires-Dist: importlib
Requires-Dist: bs4
